beth/__init__.py
beth/ai/__init__.py
beth/ai/stockfish.py
beth/ai/tree.py
beth/board.py
beth/constants.py
beth/evaluation/__init__.py
beth/evaluation/elo.py
beth/evaluation/true_skills.py
beth/game.py
beth/heuristics.py
beth/models/dataset.py
beth/models/lstm.py
beth/move.py
beth/piece.py
beth/players/__init__.py
beth/players/ai_player.py
beth/players/human_player.py
beth/players/player.py
beth/players/random_player.py
beth/players/sequence.py
beth/tree/__init__.py
beth/tree/node.py
beth/tree/tree.py
beth/utils.py
beth-0.2.0.dist-info/LICENSE
beth-0.2.0.dist-info/WHEEL
beth-0.2.0.dist-info/METADATA
beth-0.2.0.dist-info/RECORD
